{
  "$schema": "../gen/schemas/desktop-schema.json",
  "identifier": "default",
  "description": "默认权限配置",
  "windows": ["main"],
  "permissions": [
    "core:default",
    "dialog:default",
    "dialog:allow-open",
    "dialog:allow-ask",
    "dialog:allow-confirm",
    "dialog:allow-message",
    "shell:allow-execute",
    "shell:allow-spawn",
    "shell:allow-stdin-write",
    "shell:allow-kill",
    "shell:default",
    "fs:default",
    "fs:allow-appdata-read",
    "fs:allow-appdata-write",
    "fs:allow-appdata-exists",
    "event:default"
  ]
}
